Djam-0.9.8.dist-info/DESCRIPTION.rst
Djam-0.9.8.dist-info/METADATA
Djam-0.9.8.dist-info/RECORD
Djam-0.9.8.dist-info/WHEEL
Djam-0.9.8.dist-info/metadata.json
Djam-0.9.8.dist-info/top_level.txt
djam/__init__.py
djam/_django_to_sqlalchemy.py
djam/cors.py
djam/forms.py
djam/global_request.py
djam/mailutils.py
djam/middleware.py
djam/phased_views.py
djam/sqlalchemy.py
djam/thumbnailer.py
djam/utils.py
djam/world_countries.py
djam/management/__init__.py
djam/management/commands/__init__.py
djam/management/commands/syncsadb.py
djam/templatetags/__init__.py
djam/templatetags/djam.py
